pyrest/__init__.py
pyrest/cli.py
pyrest/controllers.py
pyrest/core.py
pyrest/database.py
pyrest/middlewares.py
pyrest/models.py
pyrest/request.py
pyrest/response.py
pyrest/route.py
pyrest/services.py
pyrest/utils.py
pyrest/validation.py
pyrest/templates/project_structure.py
pyrest_framework-2.0.1.dist-info/licenses/LICENSE
pyrest_framework-2.0.1.dist-info/METADATA
pyrest_framework-2.0.1.dist-info/WHEEL
pyrest_framework-2.0.1.dist-info/entry_points.txt
pyrest_framework-2.0.1.dist-info/top_level.txt
pyrest_framework-2.0.1.dist-info/RECORD
