Metadata-Version: 2.4
Name: pyrest-framework
Version: 2.0.1
Summary: Framework Python para criação de APIs REST - Estilo Express.js
Home-page: https://github.com/mamadusamadev/pyrest-framework
Author: Mamadu Sama
Author-email: Mamadu Sama <mamadusama19@gmail.com>
Maintainer-email: Mamadu Sama <mamadusama19@gmail.com>
License: MIT
Project-URL: Homepage, https://github.com/mamadusamadev/pyrest-framework
Project-URL: Documentation, https://github.com/mamadusamadev/pyrest-framework/blob/main/docs/README.md
Project-URL: Repository, https://github.com/mamadusamadev/pyrest-framework
Project-URL: Bug Tracker, https://github.com/mamadusamadev/pyrest-framework/issues
Project-URL: Changelog, https://github.com/mamadusamadev/pyrest-framework/blob/main/CHANGELOG.md
Keywords: api,rest,framework,web,http,server,express,microframework,ads,education
Platform: any
Classifier: Development Status :: 4 - Beta
Classifier: Intended Audience :: Developers
Classifier: Intended Audience :: Education
Classifier: Topic :: Software Development :: Libraries :: Python Modules
Classifier: Topic :: Internet :: WWW/HTTP :: HTTP Servers
Classifier: License :: OSI Approved :: MIT License
Classifier: Programming Language :: Python :: 3
Classifier: Programming Language :: Python :: 3.7
Classifier: Programming Language :: Python :: 3.8
Classifier: Programming Language :: Python :: 3.9
Classifier: Programming Language :: Python :: 3.10
Classifier: Programming Language :: Python :: 3.11
Classifier: Programming Language :: Python :: 3.12
Classifier: Operating System :: OS Independent
Requires-Python: >=3.7
License-File: LICENSE
Requires-Dist: prisma>=0.12.0
Requires-Dist: psycopg2-binary>=2.9.0
Requires-Dist: python-dotenv>=1.0.0
Provides-Extra: dev
Requires-Dist: pytest>=6.0; extra == "dev"
Requires-Dist: pytest-cov>=2.0; extra == "dev"
Requires-Dist: black>=21.0; extra == "dev"
Requires-Dist: flake8>=3.8; extra == "dev"
Requires-Dist: mypy>=0.800; extra == "dev"
Provides-Extra: examples
Requires-Dist: requests>=2.25.0; extra == "examples"
Provides-Extra: database
Requires-Dist: prisma>=0.12.0; extra == "database"
Requires-Dist: psycopg2-binary>=2.9.0; extra == "database"
Requires-Dist: python-dotenv>=1.0.0; extra == "database"
Requires-Dist: sqlite3; extra == "database"
Provides-Extra: postgres
Requires-Dist: prisma>=0.12.0; extra == "postgres"
Requires-Dist: psycopg2-binary>=2.9.0; extra == "postgres"
Requires-Dist: python-dotenv>=1.0.0; extra == "postgres"
Provides-Extra: mysql
Requires-Dist: prisma>=0.12.0; extra == "mysql"
Requires-Dist: mysqlclient>=2.1.0; extra == "mysql"
Requires-Dist: python-dotenv>=1.0.0; extra == "mysql"
Dynamic: author
Dynamic: home-page
Dynamic: license-file
Dynamic: platform
Dynamic: requires-python
